{
  "WeaponName": "Холодное сердце",
  "Icon": "https://bungie.net/common/destiny2_content/icons/46ebd791f692b682691416beea7ac4c5.jpg",
  "Description": "Новейшие технологии Omolon позволяют использовать жидкое топливо в качестве хладагента, обеспечивая оружейным системам минусовую температуру.",
  "DropLocation": "Можно получить за уничтожение босса в Сумрачном налете.",
  "Masterwork": "500 уничтоженных врагов человечества в любой точке Солнечной системы.",
  "Bonus": "Стабильность +20 и скорость перезарядки +20."
}